tesliper/__init__.py
tesliper/_metadata.py
tesliper/exceptions.py
tesliper/tesliper.ico
tesliper/tesliper.py
tesliper/datawork/__init__.py
tesliper/datawork/atoms.py
tesliper/datawork/energies.py
tesliper/datawork/geometry.py
tesliper/datawork/intensities.py
tesliper/datawork/spectra.py
tesliper/extraction/__init__.py
tesliper/extraction/gaussian_parser.py
tesliper/extraction/parameters_parser.py
tesliper/extraction/parser_base.py
tesliper/extraction/soxhlet.py
tesliper/extraction/spectra_parser.py
tesliper/glassware/__init__.py
tesliper/glassware/array_base.py
tesliper/glassware/arrays.py
tesliper/glassware/conformers.py
tesliper/glassware/spectra.py
tesliper/gui/__init__.py
tesliper/gui/__main__.py
tesliper/gui/main.py
tesliper/gui/components/__init__.py
tesliper/gui/components/checktree.py
tesliper/gui/components/choices.py
tesliper/gui/components/collapsible_pane.py
tesliper/gui/components/controls.py
tesliper/gui/components/helpers.py
tesliper/gui/components/hinted_entry.py
tesliper/gui/components/label_separator.py
tesliper/gui/components/numeric_entry.py
tesliper/gui/components/popups.py
tesliper/gui/components/scroll.py
tesliper/gui/components/views.py
tesliper/writing/__init__.py
tesliper/writing/csv_writer.py
tesliper/writing/gjf_writer.py
tesliper/writing/serializer.py
tesliper/writing/txt_writer.py
tesliper/writing/writer_base.py
tesliper/writing/xlsx_writer.py
tesliper-0.9.3.data/scripts/tesliper_gui.py
test/__init__.py
test/conftest.py
test/integration/__init__.py
test/integration/test_tesliper.py
test/integration/extraction/__init__.py
test/integration/extraction/test_gaussian_parser.py
test/integration/extraction/test_soxhlet.py
test/unit/__init__.py
test/unit/test_tesliper.py
test/unit/datawork/__init__.py
test/unit/datawork/test_atoms.py
test/unit/datawork/test_energies.py
test/unit/datawork/test_geometry.py
test/unit/datawork/test_spectra.py
test/unit/extraction/__init__.py
test/unit/extraction/test_extraction.py
tesliper-0.9.3.dist-info/LICENSE.txt
tesliper-0.9.3.dist-info/METADATA
tesliper-0.9.3.dist-info/WHEEL
tesliper-0.9.3.dist-info/entry_points.txt
tesliper-0.9.3.dist-info/top_level.txt
tesliper-0.9.3.dist-info/RECORD
