Metadata-Version: 2.1
Name: tesliper
Version: 0.9.3
Summary: a package for batch processing of spectra-related Gaussian output files
Home-page: https://github.com/mishioo/tesliper
Author: MichaĹ‚ M. WiÄ™cĹ‚aw
Author-email: wieclawmm@gmail.com
License: UNKNOWN
Keywords: chemistry,chemical computing,optical spectroscopy,spectral simulations,spectroscopy,Gaussian,workflow automation,batch processing
Platform: UNKNOWN
Classifier: Intended Audience :: Science/Research
Classifier: License :: OSI Approved :: BSD License
Classifier: Programming Language :: Python :: 3.6
Classifier: Programming Language :: Python :: 3.7
Classifier: Programming Language :: Python :: 3.8
Classifier: Programming Language :: Python :: 3.9
Classifier: Programming Language :: Python :: 3.10
Classifier: Topic :: Scientific/Engineering :: Chemistry
Classifier: Development Status :: 4 - Beta
Requires-Python: >=3.6
License-File: LICENSE.txt
Requires-Dist: numpy
Requires-Dist: openpyxl
Provides-Extra: build
Requires-Dist: pyinstaller ; extra == 'build'
Requires-Dist: twine ; extra == 'build'
Requires-Dist: matplotlib ; extra == 'build'
Provides-Extra: dev
Requires-Dist: black ; extra == 'dev'
Requires-Dist: pre-commit ; extra == 'dev'
Requires-Dist: flake8 ; extra == 'dev'
Requires-Dist: isort ; extra == 'dev'
Requires-Dist: matplotlib ; extra == 'dev'
Requires-Dist: pytest ; extra == 'dev'
Requires-Dist: hypothesis ; extra == 'dev'
Requires-Dist: coverage ; extra == 'dev'
Requires-Dist: pytest-cov ; extra == 'dev'
Provides-Extra: dev-all
Requires-Dist: matplotlib ; extra == 'dev-all'
Requires-Dist: pytest ; extra == 'dev-all'
Requires-Dist: hypothesis ; extra == 'dev-all'
Requires-Dist: coverage ; extra == 'dev-all'
Requires-Dist: pytest-cov ; extra == 'dev-all'
Requires-Dist: sphinx ; extra == 'dev-all'
Requires-Dist: sphinx-rtd-theme ; extra == 'dev-all'
Requires-Dist: pyinstaller ; extra == 'dev-all'
Requires-Dist: twine ; extra == 'dev-all'
Requires-Dist: black ; extra == 'dev-all'
Requires-Dist: pre-commit ; extra == 'dev-all'
Requires-Dist: flake8 ; extra == 'dev-all'
Requires-Dist: isort ; extra == 'dev-all'
Provides-Extra: docs
Requires-Dist: sphinx ; extra == 'docs'
Requires-Dist: sphinx-rtd-theme ; extra == 'docs'
Provides-Extra: gui
Requires-Dist: matplotlib ; extra == 'gui'
Provides-Extra: test
Requires-Dist: pytest ; extra == 'test'
Requires-Dist: hypothesis ; extra == 'test'
Requires-Dist: coverage ; extra == 'test'
Requires-Dist: pytest-cov ; extra == 'test'
